{
  "key": "plugin_content_manager_configuration_content_types::api::pricing.pricing",
  "value": {
    "uid": "api::pricing.pricing",
    "settings": {
      "bulkable": true,
      "filterable": true,
      "searchable": true,
      "pageSize": 10,
      "mainField": "id",
      "defaultSortBy": "id",
      "defaultSortOrder": "ASC"
    },
    "metadatas": {
      "id": {
        "edit": {},
        "list": {
          "label": "id",
          "searchable": true,
          "sortable": true
        }
      },
      "seo": {
        "edit": {
          "label": "seo",
          "description": "",
          "placeholder": "",
          "visible": true,
          "editable": true
        },
        "list": {
          "label": "seo",
          "searchable": false,
          "sortable": false
        }
      },
      "title": {
        "edit": {
          "label": "title",
          "description": "",
          "placeholder": "",
          "visible": true,
          "editable": true
        },
        "list": {
          "label": "title",
          "searchable": true,
          "sortable": true
        }
      },
      "description": {
        "edit": {
          "label": "description",
          "description": "",
          "placeholder": "",
          "visible": true,
          "editable": true
        },
        "list": {
          "label": "description",
          "searchable": true,
          "sortable": true
        }
      },
      "faqSection": {
        "edit": {
          "label": "faqSection",
          "description": "",
          "placeholder": "",
          "visible": true,
          "editable": true
        },
        "list": {
          "label": "faqSection",
          "searchable": false,
          "sortable": false
        }
      },
      "cloudSection": {
        "edit": {
          "label": "cloudSection",
          "description": "",
          "placeholder": "",
          "visible": true,
          "editable": true
        },
        "list": {
          "label": "cloudSection",
          "searchable": false,
          "sortable": false
        }
      },
      "onPremiseSection": {
        "edit": {
          "label": "onPremiseSection",
          "description": "",
          "placeholder": "",
          "visible": true,
          "editable": true
        },
        "list": {
          "label": "onPremiseSection",
          "searchable": false,
          "sortable": false
        }
      },
      "test": {
        "edit": {
          "label": "test",
          "description": "",
          "placeholder": "",
          "visible": true,
          "editable": true
        },
        "list": {
          "label": "test",
          "searchable": true,
          "sortable": true
        }
      },
      "createdAt": {
        "edit": {
          "label": "createdAt",
          "description": "",
          "placeholder": "",
          "visible": false,
          "editable": true
        },
        "list": {
          "label": "createdAt",
          "searchable": true,
          "sortable": true
        }
      },
      "updatedAt": {
        "edit": {
          "label": "updatedAt",
          "description": "",
          "placeholder": "",
          "visible": false,
          "editable": true
        },
        "list": {
          "label": "updatedAt",
          "searchable": true,
          "sortable": true
        }
      }
    },
    "layouts": {
      "list": [
        "id",
        "seo",
        "createdAt",
        "updatedAt"
      ],
      "edit": [
        [
          {
            "name": "seo",
            "size": 12
          }
        ],
        [
          {
            "name": "title",
            "size": 6
          },
          {
            "name": "description",
            "size": 6
          }
        ],
        [
          {
            "name": "faqSection",
            "size": 12
          }
        ],
        [
          {
            "name": "cloudSection",
            "size": 12
          }
        ],
        [
          {
            "name": "onPremiseSection",
            "size": 12
          }
        ],
        [
          {
            "name": "test",
            "size": 6
          }
        ]
      ]
    }
  },
  "type": "object",
  "environment": null,
  "tag": null
}