{
  "introSection": {
    "title": "About",
    "description": "<p>Gataca is a cybersecurity company founded in Boston, MA, at the heart of MIT’s entrepreneurship and innovation ecosystem. It started as an academic research study seeking to reduce the risk of doing business online, at MIT’s Media Lab in 2017. As victims of the Equifax data breach later that year, the topic became very personal.</p>"
  },
  "teamDataSection": {
    "title": "The team",
    "description": "Gataca is a cybersecurity company founded in Boston, MA, at the heart of MIT’s entrepreneurship and innovation ecosystem. It started as an academic research study seeking to reduce the risk of doing business online, at MIT’s Media Lab in 2017.",
    "team": [
      {
        "name": "Irene",
        "bio": "Lorem Ipsum",
        "photo": "../images/Irene.png",
        "links": [
          {
            "name": "linkedIn",
            "url": ""
          }
        ]
      },
      {
        "name": "Samuel",
        "bio": "Lorem Ipsum",
        "photo": "../images/Samuel.png",
        "links": [
          {
            "name": "linkedIn",
            "url": ""
          }
        ]
      },
      {
        "name": "Jose",
        "bio": "Lorem Ipsum",
        "photo": "../images/Jose.png",
        "links": [
          {
            "name": "linkedIn",
            "url": ""
          }
        ]
      },
      {
        "name": "Sergio",
        "bio": "Lorem Ipsum",
        "photo": "../images/Sergio.png",
        "links": [
          {
            "name": "linkedIn",
            "url": ""
          }
        ]
      },
      {
        "name": "Lou",
        "bio": "Lorem Ipsum",
        "photo": "../images/Lou.png",
        "links": [
          {
            "name": "linkedIn",
            "url": ""
          }
        ]
      }
    ]
  },
  "awardsDataSection": {
    "title": "Awards & Milestones",
    "awards": [
      {
        "title": "Award Title",
        "link": "",
        "photo": ""
      },
      {
        "title": "Award Title Two",
        "link": "",
        "photo": ""
      },
      {
        "title": "Award Title Two",
        "link": "",
        "photo": ""
      }
    ]
  },
  "metas": {
    "title": "",
    "description": ""
  },
  "team": [

  ]
}
